Workbook

Sheet Leia-me
A1: Galera — Modelo financeiro (dois cenários: bootstrap e captação)
A3: Este arquivo acompanha docs/business-plan.md, docs/startup/estrutura-juridica.md e docs/startup/captacao.md. Os números de preço, churn e custo fixo vêm direto da seção 7 e 8 do business-plan.md — quando um valor mudar lá, atualize aqui na aba Premissas.
A6: Abas
A7: Premissas | B7: Os números compartilhados pelos dois cenários — preço, churn, custo. Mude aqui, os dois cenários recalculam.
A8: Bootstrap | B8: Crescimento só com receita própria: fundador solo, sem aporte externo, ritmo de vendas mais lento.
A9: Investidor | B9: Mesmo modelo, com um aporte de capital (mútuo conversível) que paga uma contratação comercial e acelera o ritmo de novos clientes.
A10: Cap Table | B10: O que o aporte do cenário Investidor vira em % da empresa, dado um valuation cap, desconto e o valuation da rodada seguinte — mexa nesses três números pra testar cenários.
A11: Comparação | B11: Os dois cenários lado a lado nos meses 12 e 18.
A13: Código de cores
A14: Azul sobre fundo amarelo | B14: Premissa editável — mude aqui pra testar outro cenário.
A15: Preto | B15: Fórmula — não mude direto, ela recalcula sozinha a partir das premissas.
A16: Verde | B16: Link pra outra aba (ex.: Comparação puxando de Bootstrap/Investidor).
A18: Como as suposições foram calibradas
A19: Novos clientes pagantes/mês | B19: Rampa manual (não é fórmula) calibrada pra pousar perto do cenário 'base' do business-plan.md (~25 contas no mês 12) no Bootstrap, e acima disso no Investidor por causa da contratação comercial. Mude a rampa livremente — é suposição, não medição.
A20: Churn mensal 6% | B20: business-plan.md, seção 7 — 'alto de propósito, porque produtora pequena é sazonal'.
A21: Preço Pro Coletivo R$ 129/mês | B21: business-plan.md, seção 6.
A22: Custo fixo R$ 215/mês | B22: business-plan.md, seção 7 (Supabase + Apple Developer + domínio).
A23: Mensagens de campanha e preço/custo por mensagem | B23: business-plan.md, seção 7 — a conta de 200 convites por campanha, R$ 0,49 cobrado vs. R$ 0,35 de custo Meta.

Sheet Premissas
A1: Premissas compartilhadas
A3: Preço Pro Coletivo (assinatura mensal, R$) | B3: 129 | C3: business-plan.md §6
A4: Mensagens de campanha por conta/mês | B4: 200 | C4: business-plan.md §7 — conta de 200 convites por campanha
A5: Preço cobrado por mensagem (R$) | B5: 0.49 | C5: business-plan.md §6
A6: Custo Meta por mensagem (R$) | B6: 0.35 | C6: business-plan.md §6
A7: Custo marginal de servir por conta/mês (R$, infra) | B7: 15 | C7: business-plan.md §7
A8: Custo fixo mensal da operação (R$) | B8: 215 | C8: business-plan.md §7 — Supabase + Apple Developer + domínio
A9: Churn mensal | B9: 0.06 | C9: business-plan.md §7 — suposição de trabalho
A10: Capital inicial em caixa no mês 1 (R$) | B10: 5000 | C10: capital social de abertura da SLU — docs/startup/estrutura-juridica.md

Sheet Bootstrap
A1: Galera — Cenário Bootstrap
A3: Mês | C3: 1 | D3: 2 | E3: 3 | F3: 4 | G3: 5 | H3: 6 | I3: 7 | J3: 8 | K3: 9 | L3: 10 | M3: 11 | N3: 12 | O3: 13 | P3: 14 | Q3: 15 | R3: 16 | S3: 17 | T3: 18
A5: Novos clientes pagantes no mês | B5: premissa — mude a rampa livremente | C5: 0 | D5: 0 | E5: 1 | F5: 2 | G5: 1 | H5: 2 | I5: 2 | J5: 2 | K5: 3 | L5: 3 | M5: 3 | N5: 3 | O5: 3 | P5: 3 | Q5: 4 | R5: 4 | S5: 4 | T5: 4
A6: Clientes ativos (fim do mês) | B6: fórmula: anterior × (1 − churn) + novos | C6: =C5 -> 0 | D6: =C6*(1-Premissas!$B$9)+D5 -> 0 | E6: =D6*(1-Premissas!$B$9)+E5 -> 1 | F6: =E6*(1-Premissas!$B$9)+F5 -> 2.94 | G6: =F6*(1-Premissas!$B$9)+G5 -> 3.7636 | H6: =G6*(1-Premissas!$B$9)+H5 -> 5.537784 | I6: =H6*(1-Premissas!$B$9)+I5 -> 7.205517 | J6: =I6*(1-Premissas!$B$9)+J5 -> 8.7731859 | K6: =J6*(1-Premissas!$B$9)+K5 -> 11.246795 | ... T6: =S6*(1-Premissas!$B$9)+T5 -> 31.448799
A8: Receita — assinatura (R$) | B8: fórmula: clientes ativos × preço Pro Coletivo | C8: =C6*Premissas!$B$3 -> 0 | D8: =D6*Premissas!$B$3 -> 0 | E8: =E6*Premissas!$B$3 -> 129 | F8: =F6*Premissas!$B$3 -> 379.26 | G8: =G6*Premissas!$B$3 -> 485.5044 | H8: =H6*Premissas!$B$3 -> 714.37414 | I8: =I6*Premissas!$B$3 -> 929.51169 | J8: =J6*Premissas!$B$3 -> 1131.741 | ... T8: =T6*Premissas!$B$3 -> 4056.8951
A9: Receita — mensagens de campanha (R$) | B9: fórmula: clientes × mensagens/mês × preço/mensagem | C9: =C6*Premissas!$B$4*Premissas!$B$5 -> 0 | D9: =D6*Premissas!$B$4*Premissas!$B$5 -> 0 | E9: =E6*Premissas!$B$4*Premissas!$B$5 -> 98 | F9: =F6*Premissas!$B$4*Premissas!$B$5 -> 288.12 | G9: =G6*Premissas!$B$4*Premissas!$B$5 -> 368.8328 | H9: =H6*Premissas!$B$4*Premissas!$B$5 -> 542.70283 | I9: =I6*Premissas!$B$4*Premissas!$B$5 -> 706.14066 | J9: =J6*Premissas!$B$4*Premissas!$B$5 -> 859.77222 | ... T9: =T6*Premissas!$B$4*Premissas!$B$5 -> 3081.9823
A10: Receita total (R$) | C10: =C8+C9 -> 0 | D10: =D8+D9 -> 0 | E10: =E8+E9 -> 227 | F10: =F8+F9 -> 667.38 | G10: =G8+G9 -> 854.3372 | H10: =H8+H9 -> 1257.077 | I10: =I8+I9 -> 1635.6523 | J10: =J8+J9 -> 1991.5132 | ... T10: =T8+T9 -> 7138.8773
A12: Custo — mensagens (Meta, R$) | B12: fórmula: clientes × mensagens/mês × custo/mensagem | C12: =C6*Premissas!$B$4*Premissas!$B$6 -> 0 | D12: =D6*Premissas!$B$4*Premissas!$B$6 -> 0 | E12: =E6*Premissas!$B$4*Premissas!$B$6 -> 70 | F12: =F6*Premissas!$B$4*Premissas!$B$6 -> 205.8 | G12: =G6*Premissas!$B$4*Premissas!$B$6 -> 263.452 | H12: =H6*Premissas!$B$4*Premissas!$B$6 -> 387.64488 | I12: =I6*Premissas!$B$4*Premissas!$B$6 -> 504.38619 | J12: =J6*Premissas!$B$4*Premissas!$B$6 -> 614.12302 | ... T12: =T6*Premissas!$B$4*Premissas!$B$6 -> 2201.4159
A13: Custo — marginal de servir (infra, R$) | B13: fórmula: clientes × custo marginal/conta | C13: =C6*Premissas!$B$7 -> 0 | D13: =D6*Premissas!$B$7 -> 0 | E13: =E6*Premissas!$B$7 -> 15 | F13: =F6*Premissas!$B$7 -> 44.1 | G13: =G6*Premissas!$B$7 -> 56.454 | H13: =H6*Premissas!$B$7 -> 83.06676 | I13: =I6*Premissas!$B$7 -> 108.08275 | J13: =J6*Premissas!$B$7 -> 131.59779 | ... T13: =T6*Premissas!$B$7 -> 471.73198
A14: Custo — fixo da operação (R$) | B14: link Premissas | C14: =Premissas!$B$8 -> 215 | D14: =Premissas!$B$8 -> 215 | E14: =Premissas!$B$8 -> 215 | F14: =Premissas!$B$8 -> 215 | G14: =Premissas!$B$8 -> 215 | H14: =Premissas!$B$8 -> 215 | I14: =Premissas!$B$8 -> 215 | J14: =Premissas!$B$8 -> 215 | ... T14: =Premissas!$B$8 -> 215
A15: Custo — pró-labore do(s) fundador(es) (R$) | B15: premissa — mude a rampa | C15: 0 | D15: 0 | E15: 0 | F15: 2000 | G15: 2000 | H15: 2000 | I15: 3000 | J15: 3000 | K15: 3000 | L15: 4000 | M15: 4000 | N15: 4000 | O15: 5000 | P15: 5000 | Q15: 5000 | R15: 5000 | S15: 5000 | T15: 5000
A16: Custo — salário comercial contratado (R$) | B16: premissa — 0 antes da contratação | C16: 0 | D16: 0 | E16: 0 | F16: 0 | G16: 0 | H16: 0 | I16: 0 | J16: 0 | K16: 0 | L16: 0 | M16: 0 | N16: 0 | O16: 0 | P16: 0 | Q16: 0 | R16: 0 | S16: 0 | T16: 0
A17: Custos totais (R$) | C17: =SUM(C12:C16) -> 215 | D17: =SUM(D12:D16) -> 215 | E17: =SUM(E12:E16) -> 300 | F17: =SUM(F12:F16) -> 2464.9 | G17: =SUM(G12:G16) -> 2534.906 | H17: =SUM(H12:H16) -> 2685.7116 | I17: =SUM(I12:I16) -> 3827.4689 | J17: =SUM(J12:J16) -> 3960.7208 | ... T17: =SUM(T12:T16) -> 7888.1479
A19: Resultado mensal (R$) | B19: fórmula: receita total − custos totais | C19: =C10-C17 -> -215 | D19: =D10-D17 -> -215 | E19: =E10-E17 -> -73 | F19: =F10-F17 -> -1797.52 | G19: =G10-G17 -> -1680.5688 | H19: =H10-H17 -> -1428.6347 | I19: =I10-I17 -> -2191.8166 | J19: =J10-J17 -> -1969.2076 | ... T19: =T10-T17 -> -749.27056
A20: Aporte de investidor no mês (R$) | B20: 0 — cenário sem captação | C20: 0 | D20: 0 | E20: 0 | F20: 0 | G20: 0 | H20: 0 | I20: 0 | J20: 0 | K20: 0 | L20: 0 | M20: 0 | N20: 0 | O20: 0 | P20: 0 | Q20: 0 | R20: 0 | S20: 0 | T20: 0
A21: Caixa acumulado (R$) | B21: fórmula: caixa anterior + resultado + aporte | C21: =Premissas!$B$10+C19+C20 -> 4785 | D21: =C21+D19+D20 -> 4570 | E21: =D21+E19+E20 -> 4497 | F21: =E21+F19+F20 -> 2699.48 | G21: =F21+G19+G20 -> 1018.9112 | H21: =G21+H19+H20 -> -409.72347 | I21: =H21+I19+I20 -> -2601.5401 | J21: =I21+J19+J20 -> -4570.7477 | K21: =J21+K19+K20 -> -6188.7028 | ... T21: =S21+T19+T20 -> -21699.761
A22: Caixa ficou negativo? (1 = sim) | B22: auxiliar pro cálculo de runway | C22: =IF(C21<0,1,0) -> 0 | D22: =IF(D21<0,1,0) -> 0 | E22: =IF(E21<0,1,0) -> 0 | F22: =IF(F21<0,1,0) -> 0 | G22: =IF(G21<0,1,0) -> 0 | H22: =IF(H21<0,1,0) -> 1 | I22: =IF(I21<0,1,0) -> 1 | J22: =IF(J21<0,1,0) -> 1 | ... T22: =IF(T21<0,1,0) -> 1
A24: Runway (primeiro mês com caixa negativo) | C24: =IFERROR("mês "&MATCH(1,C22:T22,0),"não fica negativo nos 18 meses") -> mês 6

Sheet Investidor
A1: Galera — Cenário Investidor
A3: Mês | C3: 1 | D3: 2 | E3: 3 | F3: 4 | G3: 5 | H3: 6 | I3: 7 | J3: 8 | K3: 9 | L3: 10 | M3: 11 | N3: 12 | O3: 13 | P3: 14 | Q3: 15 | R3: 16 | S3: 17 | T3: 18
A5: Novos clientes pagantes no mês | B5: premissa — mude a rampa livremente | C5: 0 | D5: 0 | E5: 1 | F5: 2 | G5: 2 | H5: 3 | I5: 4 | J5: 4 | K5: 5 | L5: 5 | M5: 5 | N5: 6 | O5: 6 | P5: 7 | Q5: 7 | R5: 7 | S5: 8 | T5: 8
A6: Clientes ativos (fim do mês) | B6: fórmula: anterior × (1 − churn) + novos | C6: =C5 -> 0 | D6: =C6*(1-Premissas!$B$9)+D5 -> 0 | E6: =D6*(1-Premissas!$B$9)+E5 -> 1 | F6: =E6*(1-Premissas!$B$9)+F5 -> 2.94 | G6: =F6*(1-Premissas!$B$9)+G5 -> 4.7636 | H6: =G6*(1-Premissas!$B$9)+H5 -> 7.477784 | I6: =H6*(1-Premissas!$B$9)+I5 -> 11.029117 | J6: =I6*(1-Premissas!$B$9)+J5 -> 14.36737 | K6: =J6*(1-Premissas!$B$9)+K5 -> 18.505328 | ... T6: =S6*(1-Premissas!$B$9)+T5 -> 58.420863
A8: Receita — assinatura (R$) | B8: fórmula: clientes ativos × preço Pro Coletivo | C8: =C6*Premissas!$B$3 -> 0 | D8: =D6*Premissas!$B$3 -> 0 | E8: =E6*Premissas!$B$3 -> 129 | F8: =F6*Premissas!$B$3 -> 379.26 | G8: =G6*Premissas!$B$3 -> 614.5044 | H8: =H6*Premissas!$B$3 -> 964.63414 | I8: =I6*Premissas!$B$3 -> 1422.7561 | J8: =J6*Premissas!$B$3 -> 1853.3907 | ... T8: =T6*Premissas!$B$3 -> 7536.2913
A9: Receita — mensagens de campanha (R$) | B9: fórmula: clientes × mensagens/mês × preço/mensagem | C9: =C6*Premissas!$B$4*Premissas!$B$5 -> 0 | D9: =D6*Premissas!$B$4*Premissas!$B$5 -> 0 | E9: =E6*Premissas!$B$4*Premissas!$B$5 -> 98 | F9: =F6*Premissas!$B$4*Premissas!$B$5 -> 288.12 | G9: =G6*Premissas!$B$4*Premissas!$B$5 -> 466.8328 | H9: =H6*Premissas!$B$4*Premissas!$B$5 -> 732.82283 | I9: =I6*Premissas!$B$4*Premissas!$B$5 -> 1080.8535 | J9: =J6*Premissas!$B$4*Premissas!$B$5 -> 1408.0023 | ... T9: =T6*Premissas!$B$4*Premissas!$B$5 -> 5725.2446
A10: Receita total (R$) | C10: =C8+C9 -> 0 | D10: =D8+D9 -> 0 | E10: =E8+E9 -> 227 | F10: =F8+F9 -> 667.38 | G10: =G8+G9 -> 1081.3372 | H10: =H8+H9 -> 1697.457 | I10: =I8+I9 -> 2503.6095 | J10: =J8+J9 -> 3261.393 | ... T10: =T8+T9 -> 13261.536
A12: Custo — mensagens (Meta, R$) | B12: fórmula: clientes × mensagens/mês × custo/mensagem | C12: =C6*Premissas!$B$4*Premissas!$B$6 -> 0 | D12: =D6*Premissas!$B$4*Premissas!$B$6 -> 0 | E12: =E6*Premissas!$B$4*Premissas!$B$6 -> 70 | F12: =F6*Premissas!$B$4*Premissas!$B$6 -> 205.8 | G12: =G6*Premissas!$B$4*Premissas!$B$6 -> 333.452 | H12: =H6*Premissas!$B$4*Premissas!$B$6 -> 523.44488 | I12: =I6*Premissas!$B$4*Premissas!$B$6 -> 772.03819 | J12: =J6*Premissas!$B$4*Premissas!$B$6 -> 1005.7159 | ... T12: =T6*Premissas!$B$4*Premissas!$B$6 -> 4089.4604
A13: Custo — marginal de servir (infra, R$) | B13: fórmula: clientes × custo marginal/conta | C13: =C6*Premissas!$B$7 -> 0 | D13: =D6*Premissas!$B$7 -> 0 | E13: =E6*Premissas!$B$7 -> 15 | F13: =F6*Premissas!$B$7 -> 44.1 | G13: =G6*Premissas!$B$7 -> 71.454 | H13: =H6*Premissas!$B$7 -> 112.16676 | I13: =I6*Premissas!$B$7 -> 165.43675 | J13: =J6*Premissas!$B$7 -> 215.51055 | ... T13: =T6*Premissas!$B$7 -> 876.31294
A14: Custo — fixo da operação (R$) | B14: link Premissas | C14: =Premissas!$B$8 -> 215 | D14: =Premissas!$B$8 -> 215 | E14: =Premissas!$B$8 -> 215 | F14: =Premissas!$B$8 -> 215 | G14: =Premissas!$B$8 -> 215 | H14: =Premissas!$B$8 -> 215 | I14: =Premissas!$B$8 -> 215 | J14: =Premissas!$B$8 -> 215 | ... T14: =Premissas!$B$8 -> 215
A15: Custo — pró-labore do(s) fundador(es) (R$) | B15: premissa — mude a rampa | C15: 5000 | D15: 5000 | E15: 5000 | F15: 5000 | G15: 5000 | H15: 5000 | I15: 5000 | J15: 5000 | K15: 5000 | L15: 5000 | M15: 5000 | N15: 5000 | O15: 5000 | P15: 5000 | Q15: 5000 | R15: 5000 | S15: 5000 | T15: 5000
A16: Custo — salário comercial contratado (R$) | B16: premissa — 0 antes da contratação | C16: 0 | D16: 0 | E16: 0 | F16: 4500 | G16: 4500 | H16: 4500 | I16: 4500 | J16: 4500 | K16: 4500 | L16: 4500 | M16: 4500 | N16: 4500 | O16: 4500 | P16: 4500 | Q16: 4500 | R16: 4500 | S16: 4500 | T16: 4500
A17: Custos totais (R$) | C17: =SUM(C12:C16) -> 5215 | D17: =SUM(D12:D16) -> 5215 | E17: =SUM(E12:E16) -> 5300 | F17: =SUM(F12:F16) -> 9964.9 | G17: =SUM(G12:G16) -> 10119.906 | H17: =SUM(H12:H16) -> 10350.612 | I17: =SUM(I12:I16) -> 10652.475 | J17: =SUM(J12:J16) -> 10936.226 | ... T17: =SUM(T12:T16) -> 14680.773
A19: Resultado mensal (R$) | B19: fórmula: receita total − custos totais | C19: =C10-C17 -> -5215 | D19: =D10-D17 -> -5215 | E19: =E10-E17 -> -5073 | F19: =F10-F17 -> -9297.52 | G19: =G10-G17 -> -9038.5688 | H19: =H10-H17 -> -8653.1547 | I19: =I10-I17 -> -8148.8654 | J19: =J10-J17 -> -7674.8335 | ... T19: =T10-T17 -> -1419.2375
A20: Aporte de investidor no mês (R$) | B20: aporte de R$ 200 mil no mês 1 — ver aba Cap Table | C20: 200000 | D20: 0 | E20: 0 | F20: 0 | G20: 0 | H20: 0 | I20: 0 | J20: 0 | K20: 0 | L20: 0 | M20: 0 | N20: 0 | O20: 0 | P20: 0 | Q20: 0 | R20: 0 | S20: 0 | T20: 0
A21: Caixa acumulado (R$) | B21: fórmula: caixa anterior + resultado + aporte | C21: =Premissas!$B$10+C19+C20 -> 199785 | D21: =C21+D19+D20 -> 194570 | E21: =D21+E19+E20 -> 189497 | F21: =E21+F19+F20 -> 180199.48 | G21: =F21+G19+G20 -> 171160.91 | H21: =G21+H19+H20 -> 162507.76 | I21: =H21+I19+I20 -> 154358.89 | J21: =I21+J19+J20 -> 146684.06 | K21: =J21+K19+K20 -> 139596.81 | ... T21: =S21+T19+T20 -> 102996.39
A22: Caixa ficou negativo? (1 = sim) | B22: auxiliar pro cálculo de runway | C22: =IF(C21<0,1,0) -> 0 | D22: =IF(D21<0,1,0) -> 0 | E22: =IF(E21<0,1,0) -> 0 | F22: =IF(F21<0,1,0) -> 0 | G22: =IF(G21<0,1,0) -> 0 | H22: =IF(H21<0,1,0) -> 0 | I22: =IF(I21<0,1,0) -> 0 | J22: =IF(J21<0,1,0) -> 0 | ... T22: =IF(T21<0,1,0) -> 0
A24: Runway (primeiro mês com caixa negativo) | C24: =IFERROR("mês "&MATCH(1,C22:T22,0),"não fica negativo nos 18 meses") -> não fica negativo nos 18 meses

Sheet Cap Table
A1: Cap Table — conversão do mútuo conversível
A3: Ver docs/startup/captacao.md para o significado de cada termo.
A5: Aporte do investidor (R$) | B5: =SUM(Investidor!C20:T20) -> 200000 | C5: Link — soma da linha 'Aporte de investidor no mês' da aba Investidor
A6: Valuation cap (R$) | B6: 4000000 | C6: Premissa — docs/startup/captacao.md, faixa comum R$ 3-8 milhões em pré-seed BR
A7: Desconto de conversão | B7: 0.2 | C7: Premissa — faixa comum 15-25%
A8: Valuation da rodada seguinte (R$) | B8: 6000000 | C8: Premissa de teste — mude pra ver o efeito no % do investidor
A10: Valuation efetivo de conversão (R$) | B10: =MIN(B6,B8*(1-B7)) -> 4000000 | C10: fórmula: mínimo(valuation cap; valuation da rodada seguinte × (1 − desconto))
A11: % do investidor pós-conversão | B11: =B5/B10 -> 0.05
A12: % do fundador pós-conversão | B12: =1-B11 -> 0.95
A14: Cap table
A15: Quotista | B15: % antes do aporte | C15: % depois da conversão
A16: Fundador | B16: 1 | C16: =B12 -> 0.95
A17: Investidor-anjo | B17: 0 | C17: =B11 -> 0.05

Sheet Comparação
A1: Comparação — Bootstrap vs. Investidor
A3: Métrica | B3: Bootstrap | C3: Investidor
A4: Clientes ativos — mês 12 | B4: =Bootstrap!N6 -> 17.812208 | C4: =Investidor!N6 -> 30.488229
A5: Clientes ativos — mês 18 | B5: =Bootstrap!T6 -> 31.448799 | C5: =Investidor!T6 -> 58.420863
A6: Receita total — mês 12 (R$) | B6: =Bootstrap!N10 -> 4043.3712 | C6: =Investidor!N10 -> 6920.828
A7: Receita total — mês 18 (R$) | B7: =Bootstrap!T10 -> 7138.8773 | C7: =Investidor!T10 -> 13261.536
A8: Resultado mensal — mês 18 (R$) | B8: =Bootstrap!T19 -> -749.27056 | C8: =Investidor!T19 -> -1419.2375
A9: Caixa acumulado — mês 12 (R$) | B9: =Bootstrap!N21 -> -12139.558 | C9: =Investidor!N21 -> 121660.52
A10: Caixa acumulado — mês 18 (R$) | B10: =Bootstrap!T21 -> -21699.761 | C10: =Investidor!T21 -> 102996.39
A11: Runway | B11: =Bootstrap!C24 -> mês 6 | C11: =Investidor!C24 -> não fica negativo nos 18 meses
A13: Leitura: o cenário Investidor mostra mais clientes e mais receita porque o aporte paga uma contratação comercial (aba Investidor, linha 'salário comercial') a partir do mês 4 — o capital não é pra sobreviver, é pra acelerar o que o fundador sozinho não consegue vender ao mesmo tempo que constrói o produto (ver docs/startup/captacao.md, seção 1).
A14: Atenção ao ler 'Caixa acumulado' negativo no Bootstrap: não é a empresa quebrando, é o tamanho do aporte pessoal que o fundador precisa bancar do próprio bolso pra sustentar o pró-labore enquanto a receita ainda não cobre tudo — é exatamente o número que decide se o cenário bootstrap é viável na prática, ou se o pró-labore da aba Bootstrap (linha 15) precisa ficar mais baixo por mais tempo.
